{"note":"This file is an internal implementation detail to speed up HTML report generation. Its format can change at any time. You might be looking for the JSON report: https://coverage.rtfd.io/cmd.html#cmd-json","format":5,"version":"7.6.12","globals":"d157b0815978b894f666524a1534efae","files":{"z_6558edf98a67c6c3___init___py":{"hash":"bba43f20df27987d7f89f4c2d6c304ae","index":{"url":"z_6558edf98a67c6c3___init___py.html","file":"scrapy\\__init__.py","description":"","nums":{"precision":0,"n_files":1,"n_statements":22,"n_excluded":0,"n_missing":0,"n_branches":2,"n_partial_branches":0,"n_missing_branches":0}}},"z_6558edf98a67c6c3___main___py":{"hash":"995f7b984ddc148fe75f5d5ae4d8214a","index":{"url":"z_6558edf98a67c6c3___main___py.html","file":"scrapy\\__main__.py","description":"","nums":{"precision":0,"n_files":1,"n_statements":3,"n_excluded":0,"n_missing":3,"n_branches":2,"n_partial_branches":0,"n_missing_branches":2}}},"z_6558edf98a67c6c3_addons_py":{"hash":"f47280735d105fa9386f2e660649a8ab","index":{"url":"z_6558edf98a67c6c3_addons_py.html","file":"scrapy\\addons.py","description":"","nums":{"precision":0,"n_files":1,"n_statements":29,"n_excluded":3,"n_missing":1,"n_branches":10,"n_partial_branches":2,"n_missing_branches":2}}},"z_6558edf98a67c6c3_cmdline_py":{"hash":"cfa9a2f44df72affc4778b552b5b5903","index":{"url":"z_6558edf98a67c6c3_cmdline_py.html","file":"scrapy\\cmdline.py","description":"","nums":{"precision":0,"n_files":1,"n_statements":139,"n_excluded":5,"n_missing":30,"n_branches":52,"n_partial_branches":10,"n_missing_branches":18}}},"z_adfa160429ecdd70___init___py":{"hash":"a398461b58f17120cd80efb08e437473","index":{"url":"z_adfa160429ecdd70___init___py.html","file":"scrapy\\commands\\__init__.py","description":"","nums":{"precision":0,"n_files":1,"n_statements":87,"n_excluded":3,"n_missing":17,"n_branches":18,"n_partial_branches":5,"n_missing_branches":7}}},"z_adfa160429ecdd70_bench_py":{"hash":"27d938539914d10ead60ec89c9d3c18e","index":{"url":"z_adfa160429ecdd70_bench_py.html","file":"scrapy\\commands\\bench.py","description":"","nums":{"precision":0,"n_files":1,"n_statements":44,"n_excluded":4,"n_missing":0,"n_branches":2,"n_partial_branches":0,"n_missing_branches":0}}},"z_adfa160429ecdd70_check_py":{"hash":"ef31ec17d1ab57d1441e9f1da61c69a8","index":{"url":"z_adfa160429ecdd70_check_py.html","file":"scrapy\\commands\\check.py","description":"","nums":{"precision":0,"n_files":1,"n_statements":72,"n_excluded":0,"n_missing":1,"n_branches":24,"n_partial_branches":1,"n_missing_branches":1}}},"z_adfa160429ecdd70_crawl_py":{"hash":"86fb5737bc0935353ecf1a28dea5787e","index":{"url":"z_adfa160429ecdd70_crawl_py.html","file":"scrapy\\commands\\crawl.py","description":"","nums":{"precision":0,"n_files":1,"n_statements":24,"n_excluded":2,"n_missing":3,"n_branches":8,"n_partial_branches":3,"n_missing_branches":3}}},"z_adfa160429ecdd70_edit_py":{"hash":"a65f98ede120e3389926b82a31bfcedc","index":{"url":"z_adfa160429ecdd70_edit_py.html","file":"scrapy\\commands\\edit.py","description":"","nums":{"precision":0,"n_files":1,"n_statements":31,"n_excluded":0,"n_missing":16,"n_branches":2,"n_partial_branches":0,"n_missing_branches":2}}},"z_adfa160429ecdd70_fetch_py":{"hash":"727ce0298a28ee88dd00ccc3121dd830","index":{"url":"z_adfa160429ecdd70_fetch_py.html","file":"scrapy\\commands\\fetch.py","description":"","nums":{"precision":0,"n_files":1,"n_statements":50,"n_excluded":3,"n_missing":3,"n_branches":12,"n_partial_branches":2,"n_missing_branches":2}}},"z_adfa160429ecdd70_genspider_py":{"hash":"0e82e84389bac99c86ae9c0983b5042e","index":{"url":"z_adfa160429ecdd70_genspider_py.html","file":"scrapy\\commands\\genspider.py","description":"","nums":{"precision":0,"n_files":1,"n_statements":120,"n_excluded":2,"n_missing":8,"n_branches":38,"n_partial_branches":8,"n_missing_branches":8}}},"z_adfa160429ecdd70_list_py":{"hash":"6b7a688aae708a29b6c8d82f396a1bd0","index":{"url":"z_adfa160429ecdd70_list_py.html","file":"scrapy\\commands\\list.py","description":"","nums":{"precision":0,"n_files":1,"n_statements":12,"n_excluded":2,"n_missing":1,"n_branches":2,"n_partial_branches":1,"n_missing_branches":1}}},"z_adfa160429ecdd70_parse_py":{"hash":"164270518e1333d3ede9f63d0aac2e69","index":{"url":"z_adfa160429ecdd70_parse_py.html","file":"scrapy\\commands\\parse.py","description":"","nums":{"precision":0,"n_files":1,"n_statements":224,"n_excluded":6,"n_missing":14,"n_branches":88,"n_partial_branches":12,"n_missing_branches":16}}},"z_adfa160429ecdd70_runspider_py":{"hash":"755e53dfdc8321ea9085735ad44049fa","index":{"url":"z_adfa160429ecdd70_runspider_py.html","file":"scrapy\\commands\\runspider.py","description":"","nums":{"precision":0,"n_files":1,"n_statements":46,"n_excluded":4,"n_missing":2,"n_branches":10,"n_partial_branches":1,"n_missing_branches":1}}},"z_adfa160429ecdd70_settings_py":{"hash":"d94c0492dfe84f0787e474591ec4ee1c","index":{"url":"z_adfa160429ecdd70_settings_py.html","file":"scrapy\\commands\\settings.py","description":"","nums":{"precision":0,"n_files":1,"n_statements":34,"n_excluded":0,"n_missing":8,"n_branches":12,"n_partial_branches":1,"n_missing_branches":9}}},"z_adfa160429ecdd70_shell_py":{"hash":"e8dc64b0da9878e853ad84eeaac3f574","index":{"url":"z_adfa160429ecdd70_shell_py.html","file":"scrapy\\commands\\shell.py","description":"","nums":{"precision":0,"n_files":1,"n_statements":46,"n_excluded":3,"n_missing":2,"n_branches":6,"n_partial_branches":1,"n_missing_branches":1}}},"z_adfa160429ecdd70_startproject_py":{"hash":"6b401cc8e89823f4c98117ebf9772e2c","index":{"url":"z_adfa160429ecdd70_startproject_py.html","file":"scrapy\\commands\\startproject.py","description":"","nums":{"precision":0,"n_files":1,"n_statements":76,"n_excluded":2,"n_missing":0,"n_branches":20,"n_partial_branches":0,"n_missing_branches":0}}},"z_adfa160429ecdd70_version_py":{"hash":"dccd2febf36d18cf7ff1f3c6d3270d77","index":{"url":"z_adfa160429ecdd70_version_py.html","file":"scrapy\\commands\\version.py","description":"","nums":{"precision":0,"n_files":1,"n_statements":20,"n_excluded":0,"n_missing":0,"n_branches":4,"n_partial_branches":0,"n_missing_branches":0}}},"z_adfa160429ecdd70_view_py":{"hash":"6c2147c619718ad604123cfc9ce5bbc3","index":{"url":"z_adfa160429ecdd70_view_py.html","file":"scrapy\\commands\\view.py","description":"","nums":{"precision":0,"n_files":1,"n_statements":19,"n_excluded":0,"n_missing":4,"n_branches":2,"n_partial_branches":0,"n_missing_branches":2}}},"z_9ce37f89097b5787___init___py":{"hash":"ba37b4d2d27b046401f5e91fbd3fa7d7","index":{"url":"z_9ce37f89097b5787___init___py.html","file":"scrapy\\contracts\\__init__.py","description":"","nums":{"precision":0,"n_files":1,"n_statements":146,"n_excluded":4,"n_missing":10,"n_branches":36,"n_partial_branches":0,"n_missing_branches":2}}},"z_9ce37f89097b5787_default_py":{"hash":"dff141a88782a1e4c1304baeba842729","index":{"url":"z_9ce37f89097b5787_default_py.html","file":"scrapy\\contracts\\default.py","description":"","nums":{"precision":0,"n_files":1,"n_statements":59,"n_excluded":0,"n_missing":4,"n_branches":16,"n_partial_branches":2,"n_missing_branches":2}}},"z_fae414c435d970d4___init___py":{"hash":"b4de17c1c1f8668dc5220861c461890a","index":{"url":"z_fae414c435d970d4___init___py.html","file":"scrapy\\core\\__init__.py","description":"","nums":{"precision":0,"n_files":1,"n_statements":0,"n_excluded":0,"n_missing":0,"n_branches":0,"n_partial_branches":0,"n_missing_branches":0}}},"z_e3a1e652be7bc72d___init___py":{"hash":"438e31a4b315180a8622c1b618acbc67","index":{"url":"z_e3a1e652be7bc72d___init___py.html","file":"scrapy\\core\\downloader\\__init__.py","description":"","nums":{"precision":0,"n_files":1,"n_statements":147,"n_excluded":5,"n_missing":8,"n_branches":30,"n_partial_branches":4,"n_missing_branches":6}}},"z_e3a1e652be7bc72d_contextfactory_py":{"hash":"988f7e1addb8cb2a005f91eadaba92b0","index":{"url":"z_e3a1e652be7bc72d_contextfactory_py.html","file":"scrapy\\core\\downloader\\contextfactory.py","description":"","nums":{"precision":0,"n_files":1,"n_statements":70,"n_excluded":5,"n_missing":13,"n_branches":4,"n_partial_branches":0,"n_missing_branches":0}}},"z_8ca70c36d43ef2ee___init___py":{"hash":"b8c15cd86ea63b64868a3f016bb8f9f4","index":{"url":"z_8ca70c36d43ef2ee___init___py.html","file":"scrapy\\core\\downloader\\handlers\\__init__.py","description":"","nums":{"precision":0,"n_files":1,"n_statements":59,"n_excluded":5,"n_missing":6,"n_branches":18,"n_partial_branches":3,"n_missing_branches":3}}},"z_8ca70c36d43ef2ee_datauri_py":{"hash":"c9e977dd3bc112f79821ab289f3b9861","index":{"url":"z_8ca70c36d43ef2ee_datauri_py.html","file":"scrapy\\core\\downloader\\handlers\\datauri.py","description":"","nums":{"precision":0,"n_files":1,"n_statements":17,"n_excluded":2,"n_missing":0,"n_branches":2,"n_partial_branches":1,"n_missing_branches":1}}},"z_8ca70c36d43ef2ee_file_py":{"hash":"ca5937725bf2d00e16bf00ccc674b8a1","index":{"url":"z_8ca70c36d43ef2ee_file_py.html","file":"scrapy\\core\\downloader\\handlers\\file.py","description":"","nums":{"precision":0,"n_files":1,"n_statements":14,"n_excluded":3,"n_missing":0,"n_branches":0,"n_partial_branches":0,"n_missing_branches":0}}},"z_8ca70c36d43ef2ee_ftp_py":{"hash":"753e4d4066b42c317ea5588dff6e8284","index":{"url":"z_8ca70c36d43ef2ee_ftp_py.html","file":"scrapy\\core\\downloader\\handlers\\ftp.py","description":"","nums":{"precision":0,"n_files":1,"n_statements":71,"n_excluded":7,"n_missing":0,"n_branches":6,"n_partial_branches":1,"n_missing_branches":1}}},"z_8ca70c36d43ef2ee_http_py":{"hash":"849506b90f006007c701e6db02036e67","index":{"url":"z_8ca70c36d43ef2ee_http_py.html","file":"scrapy\\core\\downloader\\handlers\\http.py","description":"","nums":{"precision":0,"n_files":1,"n_statements":3,"n_excluded":0,"n_missing":0,"n_branches":0,"n_partial_branches":0,"n_missing_branches":0}}},"z_8ca70c36d43ef2ee_http10_py":{"hash":"8e0cda2ff8c6f7292c600180c7b32f07","index":{"url":"z_8ca70c36d43ef2ee_http10_py.html","file":"scrapy\\core\\downloader\\handlers\\http10.py","description":"","nums":{"precision":0,"n_files":1,"n_statements":28,"n_excluded":10,"n_missing":0,"n_branches":2,"n_partial_branches":0,"n_missing_branches":0}}},"z_8ca70c36d43ef2ee_http11_py":{"hash":"0a8fe547815aa5c26d5d7ee4079540d0","index":{"url":"z_8ca70c36d43ef2ee_http11_py.html","file":"scrapy\\core\\downloader\\handlers\\http11.py","description":"","nums":{"precision":0,"n_files":1,"n_statements":317,"n_excluded":6,"n_missing":10,"n_branches":62,"n_partial_branches":10,"n_missing_branches":10}}},"z_8ca70c36d43ef2ee_http2_py":{"hash":"ae21b3b0ae201500c2b5912d186ad014","index":{"url":"z_8ca70c36d43ef2ee_http2_py.html","file":"scrapy\\core\\downloader\\handlers\\http2.py","description":"","nums":{"precision":0,"n_files":1,"n_statements":63,"n_excluded":9,"n_missing":63,"n_branches":6,"n_partial_branches":0,"n_missing_branches":6}}},"z_8ca70c36d43ef2ee_s3_py":{"hash":"b33b4920cf33e9c6d3f564850fbdf336","index":{"url":"z_8ca70c36d43ef2ee_s3_py.html","file":"scrapy\\core\\downloader\\handlers\\s3.py","description":"","nums":{"precision":0,"n_files":1,"n_statements":51,"n_excluded":7,"n_missing":39,"n_branches":16,"n_partial_branches":0,"n_missing_branches":16}}},"z_e3a1e652be7bc72d_middleware_py":{"hash":"eb7b1b32cd01e6f9742f24bf0aa9480c","index":{"url":"z_e3a1e652be7bc72d_middleware_py.html","file":"scrapy\\core\\downloader\\middleware.py","description":"","nums":{"precision":0,"n_files":1,"n_statements":61,"n_excluded":5,"n_missing":1,"n_branches":28,"n_partial_branches":1,"n_missing_branches":1}}},"z_e3a1e652be7bc72d_tls_py":{"hash":"445bfcac051c60fd22241e429ee483b9","index":{"url":"z_e3a1e652be7bc72d_tls_py.html","file":"scrapy\\core\\downloader\\tls.py","description":"","nums":{"precision":0,"n_files":1,"n_statements":36,"n_excluded":0,"n_missing":1,"n_branches":10,"n_partial_branches":2,"n_missing_branches":2}}},"z_e3a1e652be7bc72d_webclient_py":{"hash":"d4c967eae7305693465a8b087a8d53f7","index":{"url":"z_e3a1e652be7bc72d_webclient_py.html","file":"scrapy\\core\\downloader\\webclient.py","description":"","nums":{"precision":0,"n_files":1,"n_statements":136,"n_excluded":2,"n_missing":7,"n_branches":32,"n_partial_branches":2,"n_missing_branches":4}}},"z_fae414c435d970d4_engine_py":{"hash":"cecf07c9c033212230d1c09211ad2519","index":{"url":"z_fae414c435d970d4_engine_py.html","file":"scrapy\\core\\engine.py","description":"","nums":{"precision":0,"n_files":1,"n_statements":267,"n_excluded":9,"n_missing":15,"n_branches":76,"n_partial_branches":14,"n_missing_branches":14}}},"z_8fbd7b0888af02f1___init___py":{"hash":"8f96e0487d400bed7b4c91e861310773","index":{"url":"z_8fbd7b0888af02f1___init___py.html","file":"scrapy\\core\\http2\\__init__.py","description":"","nums":{"precision":0,"n_files":1,"n_statements":0,"n_excluded":0,"n_missing":0,"n_branches":0,"n_partial_branches":0,"n_missing_branches":0}}},"z_8fbd7b0888af02f1_agent_py":{"hash":"c33f4f470cd5996c6ca07782ffea1db8","index":{"url":"z_8fbd7b0888af02f1_agent_py.html","file":"scrapy\\core\\http2\\agent.py","description":"","nums":{"precision":0,"n_files":1,"n_statements":81,"n_excluded":6,"n_missing":81,"n_branches":10,"n_partial_branches":0,"n_missing_branches":10}}},"z_8fbd7b0888af02f1_protocol_py":{"hash":"818b0ec679efe6d7d6e9b248e2dd2273","index":{"url":"z_8fbd7b0888af02f1_protocol_py.html","file":"scrapy\\core\\http2\\protocol.py","description":"","nums":{"precision":0,"n_files":1,"n_statements":201,"n_excluded":7,"n_missing":201,"n_branches":40,"n_partial_branches":0,"n_missing_branches":40}}},"z_8fbd7b0888af02f1_stream_py":{"hash":"56d7d1fb3fbb74df4d163faeb7080960","index":{"url":"z_8fbd7b0888af02f1_stream_py.html","file":"scrapy\\core\\http2\\stream.py","description":"","nums":{"precision":0,"n_files":1,"n_statements":170,"n_excluded":4,"n_missing":170,"n_branches":56,"n_partial_branches":0,"n_missing_branches":56}}},"z_fae414c435d970d4_scheduler_py":{"hash":"57018af5419f948110d279476f890a50","index":{"url":"z_fae414c435d970d4_scheduler_py.html","file":"scrapy\\core\\scheduler.py","description":"","nums":{"precision":0,"n_files":1,"n_statements":132,"n_excluded":8,"n_missing":9,"n_branches":26,"n_partial_branches":0,"n_missing_branches":2}}},"z_fae414c435d970d4_scraper_py":{"hash":"d9b17fb35a5e7ca56f5fa5088b197a4e","index":{"url":"z_fae414c435d970d4_scraper_py.html","file":"scrapy\\core\\scraper.py","description":"","nums":{"precision":0,"n_files":1,"n_statements":194,"n_excluded":6,"n_missing":16,"n_branches":50,"n_partial_branches":9,"n_missing_branches":13}}},"z_fae414c435d970d4_spidermw_py":{"hash":"9b275ddff748d1d7e1f6f4c702727175","index":{"url":"z_fae414c435d970d4_spidermw_py.html","file":"scrapy\\core\\spidermw.py","description":"","nums":{"precision":0,"n_files":1,"n_statements":179,"n_excluded":3,"n_missing":0,"n_branches":68,"n_partial_branches":0,"n_missing_branches":0}}},"z_6558edf98a67c6c3_crawler_py":{"hash":"db673285e18700d3af3afd4efde606ce","index":{"url":"z_6558edf98a67c6c3_crawler_py.html","file":"scrapy\\crawler.py","description":"","nums":{"precision":0,"n_files":1,"n_statements":223,"n_excluded":6,"n_missing":4,"n_branches":58,"n_partial_branches":4,"n_missing_branches":4}}},"z_faadaf17b04c62dc___init___py":{"hash":"ca2411bb2d5283cba14da3ce60f5feec","index":{"url":"z_faadaf17b04c62dc___init___py.html","file":"scrapy\\downloadermiddlewares\\__init__.py","description":"","nums":{"precision":0,"n_files":1,"n_statements":0,"n_excluded":0,"n_missing":0,"n_branches":0,"n_partial_branches":0,"n_missing_branches":0}}},"z_faadaf17b04c62dc_ajaxcrawl_py":{"hash":"24cd87f5422180bb7b9f902ebf385b51","index":{"url":"z_faadaf17b04c62dc_ajaxcrawl_py.html","file":"scrapy\\downloadermiddlewares\\ajaxcrawl.py","description":"","nums":{"precision":0,"n_files":1,"n_statements":45,"n_excluded":5,"n_missing":1,"n_branches":14,"n_partial_branches":1,"n_missing_branches":1}}},"z_faadaf17b04c62dc_cookies_py":{"hash":"1d1d12220ca9b3f053ced115a28a0057","index":{"url":"z_faadaf17b04c62dc_cookies_py.html","file":"scrapy\\downloadermiddlewares\\cookies.py","description":"","nums":{"precision":0,"n_files":1,"n_statements":112,"n_excluded":7,"n_missing":0,"n_branches":42,"n_partial_branches":2,"n_missing_branches":2}}},"z_faadaf17b04c62dc_defaultheaders_py":{"hash":"25afec957ee52ecc9f390e793255aed9","index":{"url":"z_faadaf17b04c62dc_defaultheaders_py.html","file":"scrapy\\downloadermiddlewares\\defaultheaders.py","description":"","nums":{"precision":0,"n_files":1,"n_statements":14,"n_excluded":6,"n_missing":0,"n_branches":2,"n_partial_branches":0,"n_missing_branches":0}}},"z_faadaf17b04c62dc_downloadtimeout_py":{"hash":"0f53382170dfdcb834f53a1b10d741db","index":{"url":"z_faadaf17b04c62dc_downloadtimeout_py.html","file":"scrapy\\downloadermiddlewares\\downloadtimeout.py","description":"","nums":{"precision":0,"n_files":1,"n_statements":17,"n_excluded":4,"n_missing":0,"n_branches":2,"n_partial_branches":1,"n_missing_branches":1}}},"z_faadaf17b04c62dc_httpauth_py":{"hash":"c28ad97009151b41549672ba46f0b0c1","index":{"url":"z_faadaf17b04c62dc_httpauth_py.html","file":"scrapy\\downloadermiddlewares\\httpauth.py","description":"","nums":{"precision":0,"n_files":1,"n_statements":22,"n_excluded":4,"n_missing":0,"n_branches":4,"n_partial_branches":0,"n_missing_branches":0}}},"z_faadaf17b04c62dc_httpcache_py":{"hash":"9cba43fe340ec90bfbf64f09b166063f","index":{"url":"z_faadaf17b04c62dc_httpcache_py.html","file":"scrapy\\downloadermiddlewares\\httpcache.py","description":"","nums":{"precision":0,"n_files":1,"n_statements":78,"n_excluded":8,"n_missing":4,"n_branches":26,"n_partial_branches":1,"n_missing_branches":1}}},"z_faadaf17b04c62dc_httpcompression_py":{"hash":"06d7ac88fc1c6d3d604646d3d1433f40","index":{"url":"z_faadaf17b04c62dc_httpcompression_py.html","file":"scrapy\\downloadermiddlewares\\httpcompression.py","description":"","nums":{"precision":0,"n_files":1,"n_statements":100,"n_excluded":4,"n_missing":11,"n_branches":36,"n_partial_branches":4,"n_missing_branches":4}}},"z_faadaf17b04c62dc_httpproxy_py":{"hash":"aafdba3533a9143a06dfa35ab4f08257","index":{"url":"z_faadaf17b04c62dc_httpproxy_py.html","file":"scrapy\\downloadermiddlewares\\httpproxy.py","description":"","nums":{"precision":0,"n_files":1,"n_statements":63,"n_excluded":5,"n_missing":1,"n_branches":30,"n_partial_branches":1,"n_missing_branches":1}}},"z_faadaf17b04c62dc_offsite_py":{"hash":"8aeaffa6d2c115d96db862070c70c62e","index":{"url":"z_faadaf17b04c62dc_offsite_py.html","file":"scrapy\\downloadermiddlewares\\offsite.py","description":"","nums":{"precision":0,"n_files":1,"n_statements":57,"n_excluded":4,"n_missing":2,"n_branches":14,"n_partial_branches":2,"n_missing_branches":2}}},"z_faadaf17b04c62dc_redirect_py":{"hash":"e5b82f3752d08c9aa71db0344bf57507","index":{"url":"z_faadaf17b04c62dc_redirect_py.html","file":"scrapy\\downloadermiddlewares\\redirect.py","description":"","nums":{"precision":0,"n_files":1,"n_statements":100,"n_excluded":5,"n_missing":1,"n_branches":32,"n_partial_branches":1,"n_missing_branches":1}}},"z_faadaf17b04c62dc_retry_py":{"hash":"483f70fe547d1445ef4de64ed10c12a7","index":{"url":"z_faadaf17b04c62dc_retry_py.html","file":"scrapy\\downloadermiddlewares\\retry.py","description":"","nums":{"precision":0,"n_files":1,"n_statements":61,"n_excluded":7,"n_missing":0,"n_branches":20,"n_partial_branches":0,"n_missing_branches":0}}},"z_faadaf17b04c62dc_robotstxt_py":{"hash":"eb278d58d5a110eeae3d6f88c479a892","index":{"url":"z_faadaf17b04c62dc_robotstxt_py.html","file":"scrapy\\downloadermiddlewares\\robotstxt.py","description":"","nums":{"precision":0,"n_files":1,"n_statements":90,"n_excluded":6,"n_missing":0,"n_branches":20,"n_partial_branches":0,"n_missing_branches":0}}},"z_faadaf17b04c62dc_stats_py":{"hash":"010878dae31df9f81cb7a52321b17ae1","index":{"url":"z_faadaf17b04c62dc_stats_py.html","file":"scrapy\\downloadermiddlewares\\stats.py","description":"","nums":{"precision":0,"n_files":1,"n_statements":41,"n_excluded":6,"n_missing":1,"n_branches":8,"n_partial_branches":2,"n_missing_branches":2}}},"z_faadaf17b04c62dc_useragent_py":{"hash":"17783490da7cea63e82ffc6f50511493","index":{"url":"z_faadaf17b04c62dc_useragent_py.html","file":"scrapy\\downloadermiddlewares\\useragent.py","description":"","nums":{"precision":0,"n_files":1,"n_statements":17,"n_excluded":4,"n_missing":0,"n_branches":2,"n_partial_branches":0,"n_missing_branches":0}}},"z_6558edf98a67c6c3_dupefilters_py":{"hash":"d498bfbdd438a869084ddd277f7e07c0","index":{"url":"z_6558edf98a67c6c3_dupefilters_py.html","file":"scrapy\\dupefilters.py","description":"","nums":{"precision":0,"n_files":1,"n_statements":73,"n_excluded":7,"n_missing":4,"n_branches":12,"n_partial_branches":0,"n_missing_branches":0}}},"z_6558edf98a67c6c3_exceptions_py":{"hash":"847d28aa33abd38b4faac54b70a47188","index":{"url":"z_6558edf98a67c6c3_exceptions_py.html","file":"scrapy\\exceptions.py","description":"","nums":{"precision":0,"n_files":1,"n_statements":25,"n_excluded":0,"n_missing":0,"n_branches":0,"n_partial_branches":0,"n_missing_branches":0}}},"z_6558edf98a67c6c3_exporters_py":{"hash":"e0f4b84a34b1cab6a0561c504821d60e","index":{"url":"z_6558edf98a67c6c3_exporters_py.html","file":"scrapy\\exporters.py","description":"","nums":{"precision":0,"n_files":1,"n_statements":233,"n_excluded":2,"n_missing":0,"n_branches":66,"n_partial_branches":0,"n_missing_branches":0}}},"z_6558edf98a67c6c3_extension_py":{"hash":"6c084f87617f3f9d55eb70e8ede5fedc","index":{"url":"z_6558edf98a67c6c3_extension_py.html","file":"scrapy\\extension.py","description":"","nums":{"precision":0,"n_files":1,"n_statements":9,"n_excluded":2,"n_missing":0,"n_branches":0,"n_partial_branches":0,"n_missing_branches":0}}},"z_4d6b7ebd309ab446___init___py":{"hash":"ca2411bb2d5283cba14da3ce60f5feec","index":{"url":"z_4d6b7ebd309ab446___init___py.html","file":"scrapy\\extensions\\__init__.py","description":"","nums":{"precision":0,"n_files":1,"n_statements":0,"n_excluded":0,"n_missing":0,"n_branches":0,"n_partial_branches":0,"n_missing_branches":0}}},"z_4d6b7ebd309ab446_closespider_py":{"hash":"c4bcfba33a02db148a53c3532f951fb7","index":{"url":"z_4d6b7ebd309ab446_closespider_py.html","file":"scrapy\\extensions\\closespider.py","description":"","nums":{"precision":0,"n_files":1,"n_statements":76,"n_excluded":5,"n_missing":1,"n_branches":26,"n_partial_branches":1,"n_missing_branches":1}}},"z_4d6b7ebd309ab446_corestats_py":{"hash":"00f24cf04bedeb2af12fb9b48938fa4f","index":{"url":"z_4d6b7ebd309ab446_corestats_py.html","file":"scrapy\\extensions\\corestats.py","description":"","nums":{"precision":0,"n_files":1,"n_statements":37,"n_excluded":4,"n_missing":0,"n_branches":0,"n_partial_branches":0,"n_missing_branches":0}}},"z_4d6b7ebd309ab446_debug_py":{"hash":"a33c16f92955d06e34b82e823bd6a411","index":{"url":"z_4d6b7ebd309ab446_debug_py.html","file":"scrapy\\extensions\\debug.py","description":"","nums":{"precision":0,"n_files":1,"n_statements":42,"n_excluded":4,"n_missing":42,"n_branches":2,"n_partial_branches":0,"n_missing_branches":2}}},"z_4d6b7ebd309ab446_feedexport_py":{"hash":"c8d0f84da644e0d6410fcd5f1b8244fe","index":{"url":"z_4d6b7ebd309ab446_feedexport_py.html","file":"scrapy\\extensions\\feedexport.py","description":"","nums":{"precision":0,"n_files":1,"n_statements":331,"n_excluded":8,"n_missing":38,"n_branches":70,"n_partial_branches":3,"n_missing_branches":5}}},"z_4d6b7ebd309ab446_httpcache_py":{"hash":"96a31d1204a8c8f792e0085412011b94","index":{"url":"z_4d6b7ebd309ab446_httpcache_py.html","file":"scrapy\\extensions\\httpcache.py","description":"","nums":{"precision":0,"n_files":1,"n_statements":241,"n_excluded":9,"n_missing":7,"n_branches":70,"n_partial_branches":3,"n_missing_branches":5}}},"z_4d6b7ebd309ab446_logstats_py":{"hash":"ab0741851792fd793f8c679456d29850","index":{"url":"z_4d6b7ebd309ab446_logstats_py.html","file":"scrapy\\extensions\\logstats.py","description":"","nums":{"precision":0,"n_files":1,"n_statements":56,"n_excluded":4,"n_missing":0,"n_branches":8,"n_partial_branches":0,"n_missing_branches":0}}},"z_4d6b7ebd309ab446_memdebug_py":{"hash":"ece6d96d6d0b170f906b5296c79d6e49","index":{"url":"z_4d6b7ebd309ab446_memdebug_py.html","file":"scrapy\\extensions\\memdebug.py","description":"","nums":{"precision":0,"n_files":1,"n_statements":24,"n_excluded":4,"n_missing":11,"n_branches":6,"n_partial_branches":1,"n_missing_branches":5}}},"z_4d6b7ebd309ab446_memusage_py":{"hash":"15a55d897d35e3f0e2c8b288f782c9a5","index":{"url":"z_4d6b7ebd309ab446_memusage_py.html","file":"scrapy\\extensions\\memusage.py","description":"","nums":{"precision":0,"n_files":1,"n_statements":101,"n_excluded":3,"n_missing":71,"n_branches":24,"n_partial_branches":1,"n_missing_branches":23}}},"z_4d6b7ebd309ab446_periodic_log_py":{"hash":"8d9fbbc1e02bf1049fbb783d08cae381","index":{"url":"z_4d6b7ebd309ab446_periodic_log_py.html","file":"scrapy\\extensions\\periodic_log.py","description":"","nums":{"precision":0,"n_files":1,"n_statements":87,"n_excluded":5,"n_missing":7,"n_branches":20,"n_partial_branches":4,"n_missing_branches":4}}},"z_4d6b7ebd309ab446_postprocessing_py":{"hash":"7a6fa4742a25c33bf74ab5f514f79b4c","index":{"url":"z_4d6b7ebd309ab446_postprocessing_py.html","file":"scrapy\\extensions\\postprocessing.py","description":"","nums":{"precision":0,"n_files":1,"n_statements":62,"n_excluded":0,"n_missing":1,"n_branches":2,"n_partial_branches":0,"n_missing_branches":0}}},"z_4d6b7ebd309ab446_spiderstate_py":{"hash":"4ff0085d551ef1a1a3702d17ef825142","index":{"url":"z_4d6b7ebd309ab446_spiderstate_py.html","file":"scrapy\\extensions\\spiderstate.py","description":"","nums":{"precision":0,"n_files":1,"n_statements":33,"n_excluded":3,"n_missing":0,"n_branches":6,"n_partial_branches":0,"n_missing_branches":0}}},"z_4d6b7ebd309ab446_statsmailer_py":{"hash":"eeebeb5c3495bd00da85ddc957098737","index":{"url":"z_4d6b7ebd309ab446_statsmailer_py.html","file":"scrapy\\extensions\\statsmailer.py","description":"","nums":{"precision":0,"n_files":1,"n_statements":27,"n_excluded":5,"n_missing":27,"n_branches":2,"n_partial_branches":0,"n_missing_branches":2}}},"z_4d6b7ebd309ab446_telnet_py":{"hash":"62ece4ee2da627f38a15307a3ca8a8a3","index":{"url":"z_4d6b7ebd309ab446_telnet_py.html","file":"scrapy\\extensions\\telnet.py","description":"","nums":{"precision":0,"n_files":1,"n_statements":55,"n_excluded":5,"n_missing":5,"n_branches":6,"n_partial_branches":1,"n_missing_branches":1}}},"z_4d6b7ebd309ab446_throttle_py":{"hash":"0e2035e7a9ad73cfbebfe2de348f2c2d","index":{"url":"z_4d6b7ebd309ab446_throttle_py.html","file":"scrapy\\extensions\\throttle.py","description":"","nums":{"precision":0,"n_files":1,"n_statements":57,"n_excluded":5,"n_missing":0,"n_branches":12,"n_partial_branches":0,"n_missing_branches":0}}},"z_39d7be65ab0f3d27___init___py":{"hash":"f56957420d23aae787ba4301e45459c9","index":{"url":"z_39d7be65ab0f3d27___init___py.html","file":"scrapy\\http\\__init__.py","description":"","nums":{"precision":0,"n_files":1,"n_statements":11,"n_excluded":0,"n_missing":0,"n_branches":0,"n_partial_branches":0,"n_missing_branches":0}}},"z_39d7be65ab0f3d27_cookies_py":{"hash":"9c91ab62a07ce5efc0c277670054a038","index":{"url":"z_39d7be65ab0f3d27_cookies_py.html","file":"scrapy\\http\\cookies.py","description":"","nums":{"precision":0,"n_files":1,"n_statements":120,"n_excluded":5,"n_missing":11,"n_branches":16,"n_partial_branches":1,"n_missing_branches":1}}},"z_39d7be65ab0f3d27_headers_py":{"hash":"9f27a02bc6713120b2e446470fc6a197","index":{"url":"z_39d7be65ab0f3d27_headers_py.html","file":"scrapy\\http\\headers.py","description":"","nums":{"precision":0,"n_files":1,"n_statements":72,"n_excluded":3,"n_missing":1,"n_branches":16,"n_partial_branches":0,"n_missing_branches":0}}},"z_2cb3b85df1aa044f___init___py":{"hash":"bd7c57a0840191499b0da273fa3cffe3","index":{"url":"z_2cb3b85df1aa044f___init___py.html","file":"scrapy\\http\\request\\__init__.py","description":"","nums":{"precision":0,"n_files":1,"n_statements":102,"n_excluded":6,"n_missing":1,"n_branches":32,"n_partial_branches":4,"n_missing_branches":4}}},"z_2cb3b85df1aa044f_form_py":{"hash":"252e4c84abc4c2dfc08c30debd371441","index":{"url":"z_2cb3b85df1aa044f_form_py.html","file":"scrapy\\http\\request\\form.py","description":"","nums":{"precision":0,"n_files":1,"n_statements":129,"n_excluded":3,"n_missing":0,"n_branches":54,"n_partial_branches":1,"n_missing_branches":1}}},"z_2cb3b85df1aa044f_json_request_py":{"hash":"e256398abcc4b0ebf529f579bdc3d68f","index":{"url":"z_2cb3b85df1aa044f_json_request_py.html","file":"scrapy\\http\\request\\json_request.py","description":"","nums":{"precision":0,"n_files":1,"n_statements":42,"n_excluded":2,"n_missing":0,"n_branches":14,"n_partial_branches":2,"n_missing_branches":2}}},"z_2cb3b85df1aa044f_rpc_py":{"hash":"d43d4f4d725dd6a72c543504ed7415f0","index":{"url":"z_2cb3b85df1aa044f_rpc_py.html","file":"scrapy\\http\\request\\rpc.py","description":"","nums":{"precision":0,"n_files":1,"n_statements":19,"n_excluded":0,"n_missing":0,"n_branches":4,"n_partial_branches":0,"n_missing_branches":0}}},"z_d6ddde61f7835295___init___py":{"hash":"a70dda408646c8bae49e16489edb9104","index":{"url":"z_d6ddde61f7835295___init___py.html","file":"scrapy\\http\\response\\__init__.py","description":"","nums":{"precision":0,"n_files":1,"n_statements":88,"n_excluded":8,"n_missing":1,"n_branches":22,"n_partial_branches":3,"n_missing_branches":3}}},"z_d6ddde61f7835295_html_py":{"hash":"4cc7d12d0ffb86bd9b019727ccc35299","index":{"url":"z_d6ddde61f7835295_html_py.html","file":"scrapy\\http\\response\\html.py","description":"","nums":{"precision":0,"n_files":1,"n_statements":3,"n_excluded":0,"n_missing":0,"n_branches":0,"n_partial_branches":0,"n_missing_branches":0}}},"z_d6ddde61f7835295_json_py":{"hash":"079c064579c3ef90e10f5fade1929241","index":{"url":"z_d6ddde61f7835295_json_py.html","file":"scrapy\\http\\response\\json.py","description":"","nums":{"precision":0,"n_files":1,"n_statements":3,"n_excluded":0,"n_missing":0,"n_branches":0,"n_partial_branches":0,"n_missing_branches":0}}},"z_d6ddde61f7835295_text_py":{"hash":"61cb0b812350ba66cdef36cd8bb5a18a","index":{"url":"z_d6ddde61f7835295_text_py.html","file":"scrapy\\http\\response\\text.py","description":"","nums":{"precision":0,"n_files":1,"n_statements":124,"n_excluded":6,"n_missing":1,"n_branches":40,"n_partial_branches":1,"n_missing_branches":1}}},"z_d6ddde61f7835295_xml_py":{"hash":"d0eec2e53fe961a77ad5d4cfc0a6a7d0","index":{"url":"z_d6ddde61f7835295_xml_py.html","file":"scrapy\\http\\response\\xml.py","description":"","nums":{"precision":0,"n_files":1,"n_statements":3,"n_excluded":0,"n_missing":0,"n_branches":0,"n_partial_branches":0,"n_missing_branches":0}}},"z_6558edf98a67c6c3_interfaces_py":{"hash":"99ac757e98318b7412a972dff9f124f0","index":{"url":"z_6558edf98a67c6c3_interfaces_py.html","file":"scrapy\\interfaces.py","description":"","nums":{"precision":0,"n_files":1,"n_statements":6,"n_excluded":0,"n_missing":0,"n_branches":0,"n_partial_branches":0,"n_missing_branches":0}}},"z_6558edf98a67c6c3_item_py":{"hash":"b70b065f74cce4a2dedb9e249acea1e0","index":{"url":"z_6558edf98a67c6c3_item_py.html","file":"scrapy\\item.py","description":"","nums":{"precision":0,"n_files":1,"n_statements":62,"n_excluded":3,"n_missing":1,"n_branches":18,"n_partial_branches":0,"n_missing_branches":0}}},"z_6558edf98a67c6c3_link_py":{"hash":"e6db85ebac0a032e5466e6c50a9733ee","index":{"url":"z_6558edf98a67c6c3_link_py.html","file":"scrapy\\link.py","description":"","nums":{"precision":0,"n_files":1,"n_statements":18,"n_excluded":0,"n_missing":1,"n_branches":4,"n_partial_branches":1,"n_missing_branches":1}}},"z_53e8075e818fcab6___init___py":{"hash":"ad3fdae13360762064c56746a3f65a14","index":{"url":"z_53e8075e818fcab6___init___py.html","file":"scrapy\\linkextractors\\__init__.py","description":"","nums":{"precision":0,"n_files":1,"n_statements":9,"n_excluded":3,"n_missing":0,"n_branches":0,"n_partial_branches":0,"n_missing_branches":0}}},"z_53e8075e818fcab6_lxmlhtml_py":{"hash":"c4b0da738f45aac1bad30ab3b72ea696","index":{"url":"z_53e8075e818fcab6_lxmlhtml_py.html","file":"scrapy\\linkextractors\\lxmlhtml.py","description":"","nums":{"precision":0,"n_files":1,"n_statements":140,"n_excluded":4,"n_missing":2,"n_branches":46,"n_partial_branches":1,"n_missing_branches":1}}},"z_4252bef592775da3___init___py":{"hash":"f4c4583844c00accf33c70df4b92e622","index":{"url":"z_4252bef592775da3___init___py.html","file":"scrapy\\loader\\__init__.py","description":"","nums":{"precision":0,"n_files":1,"n_statements":16,"n_excluded":2,"n_missing":0,"n_branches":2,"n_partial_branches":0,"n_missing_branches":0}}},"z_6558edf98a67c6c3_logformatter_py":{"hash":"4976eacd9d1a86bd2465caefab2fb80c","index":{"url":"z_6558edf98a67c6c3_logformatter_py.html","file":"scrapy\\logformatter.py","description":"","nums":{"precision":0,"n_files":1,"n_statements":52,"n_excluded":3,"n_missing":1,"n_branches":10,"n_partial_branches":1,"n_missing_branches":1}}},"z_6558edf98a67c6c3_mail_py":{"hash":"483b9bb36817ecfae7ef582a1c55e2dd","index":{"url":"z_6558edf98a67c6c3_mail_py.html","file":"scrapy\\mail.py","description":"","nums":{"precision":0,"n_files":1,"n_statements":97,"n_excluded":7,"n_missing":22,"n_branches":16,"n_partial_branches":3,"n_missing_branches":5}}},"z_6558edf98a67c6c3_middleware_py":{"hash":"0f4b9576cb24579cc0afce68d59aeb2e","index":{"url":"z_6558edf98a67c6c3_middleware_py.html","file":"scrapy\\middleware.py","description":"","nums":{"precision":0,"n_files":1,"n_statements":72,"n_excluded":8,"n_missing":12,"n_branches":16,"n_partial_branches":1,"n_missing_branches":5}}},"z_778e0324421592aa___init___py":{"hash":"a29456178a12bac6fd8fad479684004d","index":{"url":"z_778e0324421592aa___init___py.html","file":"scrapy\\pipelines\\__init__.py","description":"","nums":{"precision":0,"n_files":1,"n_statements":16,"n_excluded":4,"n_missing":0,"n_branches":2,"n_partial_branches":0,"n_missing_branches":0}}},"z_778e0324421592aa_files_py":{"hash":"e22b0f663e2c7b8fcab99933cf31fe77","index":{"url":"z_778e0324421592aa_files_py.html","file":"scrapy\\pipelines\\files.py","description":"","nums":{"precision":0,"n_files":1,"n_statements":345,"n_excluded":7,"n_missing":75,"n_branches":68,"n_partial_branches":12,"n_missing_branches":28}}},"z_778e0324421592aa_images_py":{"hash":"8fa09a56a71f504583dffe4ed1561483","index":{"url":"z_778e0324421592aa_images_py.html","file":"scrapy\\pipelines\\images.py","description":"","nums":{"precision":0,"n_files":1,"n_statements":119,"n_excluded":8,"n_missing":85,"n_branches":32,"n_partial_branches":0,"n_missing_branches":32}}},"z_778e0324421592aa_media_py":{"hash":"1a49e1ca1aeef0058d12ece93a4f98d0","index":{"url":"z_778e0324421592aa_media_py.html","file":"scrapy\\pipelines\\media.py","description":"","nums":{"precision":0,"n_files":1,"n_statements":161,"n_excluded":7,"n_missing":8,"n_branches":46,"n_partial_branches":3,"n_missing_branches":3}}},"z_6558edf98a67c6c3_pqueues_py":{"hash":"6dc7c28337e5b7009f721405a5fe1dbe","index":{"url":"z_6558edf98a67c6c3_pqueues_py.html","file":"scrapy\\pqueues.py","description":"","nums":{"precision":0,"n_files":1,"n_statements":130,"n_excluded":5,"n_missing":1,"n_branches":40,"n_partial_branches":4,"n_missing_branches":4}}},"z_6558edf98a67c6c3_resolver_py":{"hash":"bf38a24a9e7023a6f072ee3d1d826dda","index":{"url":"z_6558edf98a67c6c3_resolver_py.html","file":"scrapy\\resolver.py","description":"","nums":{"precision":0,"n_files":1,"n_statements":79,"n_excluded":5,"n_missing":3,"n_branches":12,"n_partial_branches":3,"n_missing_branches":3}}},"z_6558edf98a67c6c3_responsetypes_py":{"hash":"8ea2b6e6d6ca7317710e20723f959430","index":{"url":"z_6558edf98a67c6c3_responsetypes_py.html","file":"scrapy\\responsetypes.py","description":"","nums":{"precision":0,"n_files":1,"n_statements":74,"n_excluded":2,"n_missing":4,"n_branches":32,"n_partial_branches":2,"n_missing_branches":2}}},"z_6558edf98a67c6c3_robotstxt_py":{"hash":"630b358bad53124c2903c96602223fe0","index":{"url":"z_6558edf98a67c6c3_robotstxt_py.html","file":"scrapy\\robotstxt.py","description":"","nums":{"precision":0,"n_files":1,"n_statements":66,"n_excluded":4,"n_missing":10,"n_branches":2,"n_partial_branches":0,"n_missing_branches":0}}},"z_542e773f0cc1cb67___init___py":{"hash":"d929d6d68eda8773609b2dbe63529500","index":{"url":"z_542e773f0cc1cb67___init___py.html","file":"scrapy\\selector\\__init__.py","description":"","nums":{"precision":0,"n_files":1,"n_statements":2,"n_excluded":0,"n_missing":0,"n_branches":0,"n_partial_branches":0,"n_missing_branches":0}}},"z_542e773f0cc1cb67_unified_py":{"hash":"071b1e69c2e5f42305387485262412ec","index":{"url":"z_542e773f0cc1cb67_unified_py.html","file":"scrapy\\selector\\unified.py","description":"","nums":{"precision":0,"n_files":1,"n_statements":33,"n_excluded":0,"n_missing":0,"n_branches":10,"n_partial_branches":0,"n_missing_branches":0}}},"z_52d5f0a6c4307219___init___py":{"hash":"01d869a416c46cbb0f03c85311f69f0c","index":{"url":"z_52d5f0a6c4307219___init___py.html","file":"scrapy\\settings\\__init__.py","description":"","nums":{"precision":0,"n_files":1,"n_statements":194,"n_excluded":5,"n_missing":4,"n_branches":76,"n_partial_branches":1,"n_missing_branches":3}}},"z_52d5f0a6c4307219_default_settings_py":{"hash":"64d13bd52c251d3eab7c819735f63ad5","index":{"url":"z_52d5f0a6c4307219_default_settings_py.html","file":"scrapy\\settings\\default_settings.py","description":"","nums":{"precision":0,"n_files":1,"n_statements":170,"n_excluded":0,"n_missing":0,"n_branches":2,"n_partial_branches":1,"n_missing_branches":1}}},"z_6558edf98a67c6c3_shell_py":{"hash":"4f46514b96e0f0f6cac87ac3963608a1","index":{"url":"z_6558edf98a67c6c3_shell_py.html","file":"scrapy\\shell.py","description":"","nums":{"precision":0,"n_files":1,"n_statements":139,"n_excluded":2,"n_missing":12,"n_branches":36,"n_partial_branches":8,"n_missing_branches":10}}},"z_6558edf98a67c6c3_signalmanager_py":{"hash":"09abef82ce89c351a6c00f284302d149","index":{"url":"z_6558edf98a67c6c3_signalmanager_py.html","file":"scrapy\\signalmanager.py","description":"","nums":{"precision":0,"n_files":1,"n_statements":22,"n_excluded":2,"n_missing":2,"n_branches":0,"n_partial_branches":0,"n_missing_branches":0}}},"z_6558edf98a67c6c3_signals_py":{"hash":"faea5a45ca1bcc30adaa2e85ef467f5f","index":{"url":"z_6558edf98a67c6c3_signals_py.html","file":"scrapy\\signals.py","description":"","nums":{"precision":0,"n_files":1,"n_statements":19,"n_excluded":0,"n_missing":0,"n_branches":0,"n_partial_branches":0,"n_missing_branches":0}}},"z_6558edf98a67c6c3_spiderloader_py":{"hash":"7a5a72be7fc82522bebb073fd655fe06","index":{"url":"z_6558edf98a67c6c3_spiderloader_py.html","file":"scrapy\\spiderloader.py","description":"","nums":{"precision":0,"n_files":1,"n_statements":50,"n_excluded":5,"n_missing":0,"n_branches":12,"n_partial_branches":0,"n_missing_branches":0}}},"z_d83cc0023b40efc7___init___py":{"hash":"ca2411bb2d5283cba14da3ce60f5feec","index":{"url":"z_d83cc0023b40efc7___init___py.html","file":"scrapy\\spidermiddlewares\\__init__.py","description":"","nums":{"precision":0,"n_files":1,"n_statements":0,"n_excluded":0,"n_missing":0,"n_branches":0,"n_partial_branches":0,"n_missing_branches":0}}},"z_d83cc0023b40efc7_depth_py":{"hash":"08a7e6f8ae4296df9bad0a17bd14ab39","index":{"url":"z_d83cc0023b40efc7_depth_py.html","file":"scrapy\\spidermiddlewares\\depth.py","description":"","nums":{"precision":0,"n_files":1,"n_statements":46,"n_excluded":6,"n_missing":0,"n_branches":16,"n_partial_branches":1,"n_missing_branches":1}}},"z_d83cc0023b40efc7_httperror_py":{"hash":"79b0d67e923893d7721b4c6ef61a65ed","index":{"url":"z_d83cc0023b40efc7_httperror_py.html","file":"scrapy\\spidermiddlewares\\httperror.py","description":"","nums":{"precision":0,"n_files":1,"n_statements":38,"n_excluded":7,"n_missing":0,"n_branches":12,"n_partial_branches":0,"n_missing_branches":0}}},"z_d83cc0023b40efc7_offsite_py":{"hash":"a336031a596931976b579592ee3a6f02","index":{"url":"z_d83cc0023b40efc7_offsite_py.html","file":"scrapy\\spidermiddlewares\\offsite.py","description":"","nums":{"precision":0,"n_files":1,"n_statements":68,"n_excluded":5,"n_missing":4,"n_branches":20,"n_partial_branches":1,"n_missing_branches":5}}},"z_d83cc0023b40efc7_referer_py":{"hash":"da7c0753d950c55779730565d6e8681b","index":{"url":"z_d83cc0023b40efc7_referer_py.html","file":"scrapy\\spidermiddlewares\\referer.py","description":"","nums":{"precision":0,"n_files":1,"n_statements":157,"n_excluded":5,"n_missing":5,"n_branches":50,"n_partial_branches":5,"n_missing_branches":5}}},"z_d83cc0023b40efc7_urllength_py":{"hash":"8318efd12b8693c761f425e0661223c4","index":{"url":"z_d83cc0023b40efc7_urllength_py.html","file":"scrapy\\spidermiddlewares\\urllength.py","description":"","nums":{"precision":0,"n_files":1,"n_statements":36,"n_excluded":6,"n_missing":3,"n_branches":8,"n_partial_branches":2,"n_missing_branches":2}}},"z_33d124893a1e9b33___init___py":{"hash":"5d151e8e763405ce519b375bc76c6a01","index":{"url":"z_33d124893a1e9b33___init___py.html","file":"scrapy\\spiders\\__init__.py","description":"","nums":{"precision":0,"n_files":1,"n_statements":61,"n_excluded":10,"n_missing":0,"n_branches":12,"n_partial_branches":0,"n_missing_branches":0}}},"z_33d124893a1e9b33_crawl_py":{"hash":"dcb2d40860ccc809a18a478b13cda28b","index":{"url":"z_33d124893a1e9b33_crawl_py.html","file":"scrapy\\spiders\\crawl.py","description":"","nums":{"precision":0,"n_files":1,"n_statements":97,"n_excluded":5,"n_missing":0,"n_branches":26,"n_partial_branches":3,"n_missing_branches":3}}},"z_33d124893a1e9b33_feed_py":{"hash":"8ee89e2486369e17137df52c44ad2a59","index":{"url":"z_33d124893a1e9b33_feed_py.html","file":"scrapy\\spiders\\feed.py","description":"","nums":{"precision":0,"n_files":1,"n_statements":70,"n_excluded":2,"n_missing":18,"n_branches":24,"n_partial_branches":3,"n_missing_branches":11}}},"z_33d124893a1e9b33_init_py":{"hash":"450fb7e5d95cabe91e7cf1319153ab93","index":{"url":"z_33d124893a1e9b33_init_py.html","file":"scrapy\\spiders\\init.py","description":"","nums":{"precision":0,"n_files":1,"n_statements":14,"n_excluded":2,"n_missing":0,"n_branches":0,"n_partial_branches":0,"n_missing_branches":0}}},"z_33d124893a1e9b33_sitemap_py":{"hash":"c0dae43efe558e70135b0fe8ce1b4a42","index":{"url":"z_33d124893a1e9b33_sitemap_py.html","file":"scrapy\\spiders\\sitemap.py","description":"","nums":{"precision":0,"n_files":1,"n_statements":83,"n_excluded":4,"n_missing":4,"n_branches":40,"n_partial_branches":8,"n_missing_branches":8}}},"z_6558edf98a67c6c3_squeues_py":{"hash":"7063dc0a4c7d881d44c1e8437b8aacad","index":{"url":"z_6558edf98a67c6c3_squeues_py.html","file":"scrapy\\squeues.py","description":"","nums":{"precision":0,"n_files":1,"n_statements":83,"n_excluded":6,"n_missing":4,"n_branches":10,"n_partial_branches":0,"n_missing_branches":0}}},"z_6558edf98a67c6c3_statscollectors_py":{"hash":"e856504de6e866d43d0cc49aedaea7d5","index":{"url":"z_6558edf98a67c6c3_statscollectors_py.html","file":"scrapy\\statscollectors.py","description":"","nums":{"precision":0,"n_files":1,"n_statements":54,"n_excluded":3,"n_missing":3,"n_branches":2,"n_partial_branches":1,"n_missing_branches":1}}},"z_6167d61523e461a5___init___py":{"hash":"ca2411bb2d5283cba14da3ce60f5feec","index":{"url":"z_6167d61523e461a5___init___py.html","file":"scrapy\\utils\\__init__.py","description":"","nums":{"precision":0,"n_files":1,"n_statements":0,"n_excluded":0,"n_missing":0,"n_branches":0,"n_partial_branches":0,"n_missing_branches":0}}},"z_6167d61523e461a5__compression_py":{"hash":"b9efa7099ad86bcdca1f9ac85cc6b877","index":{"url":"z_6167d61523e461a5__compression_py.html","file":"scrapy\\utils\\_compression.py","description":"","nums":{"precision":0,"n_files":1,"n_statements":76,"n_excluded":0,"n_missing":9,"n_branches":14,"n_partial_branches":1,"n_missing_branches":1}}},"z_6167d61523e461a5_asyncgen_py":{"hash":"7f7644af2952290f5630808d17976c09","index":{"url":"z_6167d61523e461a5_asyncgen_py.html","file":"scrapy\\utils\\asyncgen.py","description":"","nums":{"precision":0,"n_files":1,"n_statements":12,"n_excluded":0,"n_missing":0,"n_branches":6,"n_partial_branches":0,"n_missing_branches":0}}},"z_6167d61523e461a5_benchserver_py":{"hash":"886aaa86ba19f110bd3b28aa43f8a1ea","index":{"url":"z_6167d61523e461a5_benchserver_py.html","file":"scrapy\\utils\\benchserver.py","description":"","nums":{"precision":0,"n_files":1,"n_statements":34,"n_excluded":0,"n_missing":34,"n_branches":4,"n_partial_branches":0,"n_missing_branches":4}}},"z_6167d61523e461a5_boto_py":{"hash":"73efcd3c34eea4bb122d7a5981eba8b6","index":{"url":"z_6167d61523e461a5_boto_py.html","file":"scrapy\\utils\\boto.py","description":"","nums":{"precision":0,"n_files":1,"n_statements":6,"n_excluded":0,"n_missing":5,"n_branches":0,"n_partial_branches":0,"n_missing_branches":0}}},"z_6167d61523e461a5_conf_py":{"hash":"2c6ed17f057c21b081ab61a47e1262f5","index":{"url":"z_6167d61523e461a5_conf_py.html","file":"scrapy\\utils\\conf.py","description":"","nums":{"precision":0,"n_files":1,"n_statements":104,"n_excluded":2,"n_missing":3,"n_branches":38,"n_partial_branches":4,"n_missing_branches":4}}},"z_6167d61523e461a5_console_py":{"hash":"671d4b38a905919f4f3e66505c494f6a","index":{"url":"z_6167d61523e461a5_console_py.html","file":"scrapy\\utils\\console.py","description":"","nums":{"precision":0,"n_files":1,"n_statements":67,"n_excluded":2,"n_missing":32,"n_branches":12,"n_partial_branches":4,"n_missing_branches":4}}},"z_6167d61523e461a5_curl_py":{"hash":"26e0c9c893a6d6e78dacb09053c9d45e","index":{"url":"z_6167d61523e461a5_curl_py.html","file":"scrapy\\utils\\curl.py","description":"","nums":{"precision":0,"n_files":1,"n_statements":67,"n_excluded":2,"n_missing":0,"n_branches":26,"n_partial_branches":0,"n_missing_branches":0}}},"z_6167d61523e461a5_datatypes_py":{"hash":"7756897224dfed12e0c7f2817c9776c5","index":{"url":"z_6167d61523e461a5_datatypes_py.html","file":"scrapy\\utils\\datatypes.py","description":"","nums":{"precision":0,"n_files":1,"n_statements":106,"n_excluded":3,"n_missing":0,"n_branches":8,"n_partial_branches":0,"n_missing_branches":0}}},"z_6167d61523e461a5_decorators_py":{"hash":"4c955c81b3b639b44f06ffe0af98325e","index":{"url":"z_6167d61523e461a5_decorators_py.html","file":"scrapy\\utils\\decorators.py","description":"","nums":{"precision":0,"n_files":1,"n_statements":32,"n_excluded":4,"n_missing":17,"n_branches":4,"n_partial_branches":0,"n_missing_branches":4}}},"z_6167d61523e461a5_defer_py":{"hash":"479694bfc906a48670be649a10aa4509","index":{"url":"z_6167d61523e461a5_defer_py.html","file":"scrapy\\utils\\defer.py","description":"","nums":{"precision":0,"n_files":1,"n_statements":170,"n_excluded":5,"n_missing":11,"n_branches":44,"n_partial_branches":6,"n_missing_branches":10}}},"z_6167d61523e461a5_deprecate_py":{"hash":"1b01279f94f84145c1977e6c4dce4266","index":{"url":"z_6167d61523e461a5_deprecate_py.html","file":"scrapy\\utils\\deprecate.py","description":"","nums":{"precision":0,"n_files":1,"n_statements":71,"n_excluded":0,"n_missing":2,"n_branches":24,"n_partial_branches":3,"n_missing_branches":3}}},"z_6167d61523e461a5_display_py":{"hash":"e390bfd42459d3affa569f69ce1b11f1","index":{"url":"z_6167d61523e461a5_display_py.html","file":"scrapy\\utils\\display.py","description":"","nums":{"precision":0,"n_files":1,"n_statements":29,"n_excluded":0,"n_missing":2,"n_branches":6,"n_partial_branches":0,"n_missing_branches":0}}},"z_6167d61523e461a5_engine_py":{"hash":"14fa14a47aaa1a3f31d445a70fcebd87","index":{"url":"z_6167d61523e461a5_engine_py.html","file":"scrapy\\utils\\engine.py","description":"","nums":{"precision":0,"n_files":1,"n_statements":21,"n_excluded":2,"n_missing":3,"n_branches":4,"n_partial_branches":0,"n_missing_branches":0}}},"z_6167d61523e461a5_ftp_py":{"hash":"ddaadf14aa09d9dcd32aeced37197e7e","index":{"url":"z_6167d61523e461a5_ftp_py.html","file":"scrapy\\utils\\ftp.py","description":"","nums":{"precision":0,"n_files":1,"n_statements":24,"n_excluded":0,"n_missing":0,"n_branches":4,"n_partial_branches":1,"n_missing_branches":1}}},"z_6167d61523e461a5_gz_py":{"hash":"2873a38cb4e9938954d1d0a68d570540","index":{"url":"z_6167d61523e461a5_gz_py.html","file":"scrapy\\utils\\gz.py","description":"","nums":{"precision":0,"n_files":1,"n_statements":26,"n_excluded":2,"n_missing":0,"n_branches":6,"n_partial_branches":0,"n_missing_branches":0}}},"z_6167d61523e461a5_httpobj_py":{"hash":"590e2e7751985ae1d67d32045541c42a","index":{"url":"z_6167d61523e461a5_httpobj_py.html","file":"scrapy\\utils\\httpobj.py","description":"","nums":{"precision":0,"n_files":1,"n_statements":9,"n_excluded":2,"n_missing":0,"n_branches":2,"n_partial_branches":0,"n_missing_branches":0}}},"z_6167d61523e461a5_iterators_py":{"hash":"e976b6fb0aeb9bef1a5e44afc64bffb9","index":{"url":"z_6167d61523e461a5_iterators_py.html","file":"scrapy\\utils\\iterators.py","description":"","nums":{"precision":0,"n_files":1,"n_statements":133,"n_excluded":2,"n_missing":5,"n_branches":58,"n_partial_branches":6,"n_missing_branches":6}}},"z_6167d61523e461a5_job_py":{"hash":"efb790784d2bc09940a078a4de2efe73","index":{"url":"z_6167d61523e461a5_job_py.html","file":"scrapy\\utils\\job.py","description":"","nums":{"precision":0,"n_files":1,"n_statements":10,"n_excluded":2,"n_missing":1,"n_branches":4,"n_partial_branches":1,"n_missing_branches":1}}},"z_6167d61523e461a5_log_py":{"hash":"5ba63284f65ec4dbe9459735b7941d01","index":{"url":"z_6167d61523e461a5_log_py.html","file":"scrapy\\utils\\log.py","description":"","nums":{"precision":0,"n_files":1,"n_statements":108,"n_excluded":3,"n_missing":3,"n_branches":30,"n_partial_branches":3,"n_missing_branches":5}}},"z_6167d61523e461a5_misc_py":{"hash":"37f2d46aa4e4120e34a648cfa2134870","index":{"url":"z_6167d61523e461a5_misc_py.html","file":"scrapy\\utils\\misc.py","description":"","nums":{"precision":0,"n_files":1,"n_statements":146,"n_excluded":5,"n_missing":8,"n_branches":56,"n_partial_branches":0,"n_missing_branches":2}}},"z_6167d61523e461a5_ossignal_py":{"hash":"958ed443bd183e4cfeea5d3167cb96b4","index":{"url":"z_6167d61523e461a5_ossignal_py.html","file":"scrapy\\utils\\ossignal.py","description":"","nums":{"precision":0,"n_files":1,"n_statements":18,"n_excluded":0,"n_missing":0,"n_branches":10,"n_partial_branches":3,"n_missing_branches":3}}},"z_6167d61523e461a5_project_py":{"hash":"b895a7b46f74682fea0b87e4a891aa51","index":{"url":"z_6167d61523e461a5_project_py.html","file":"scrapy\\utils\\project.py","description":"","nums":{"precision":0,"n_files":1,"n_statements":53,"n_excluded":0,"n_missing":6,"n_branches":20,"n_partial_branches":5,"n_missing_branches":5}}},"z_6167d61523e461a5_python_py":{"hash":"dbacef9d932fc228613bad22b7f00a4e","index":{"url":"z_6167d61523e461a5_python_py.html","file":"scrapy\\utils\\python.py","description":"","nums":{"precision":0,"n_files":1,"n_statements":166,"n_excluded":5,"n_missing":20,"n_branches":70,"n_partial_branches":9,"n_missing_branches":15}}},"z_6167d61523e461a5_reactor_py":{"hash":"784f0c8e00e8474fffdadbd4963408f8","index":{"url":"z_6167d61523e461a5_reactor_py.html","file":"scrapy\\utils\\reactor.py","description":"","nums":{"precision":0,"n_files":1,"n_statements":90,"n_excluded":8,"n_missing":17,"n_branches":24,"n_partial_branches":6,"n_missing_branches":8}}},"z_6167d61523e461a5_request_py":{"hash":"9269d570bcc12eaac42e8b17be3da95c","index":{"url":"z_6167d61523e461a5_request_py.html","file":"scrapy\\utils\\request.py","description":"","nums":{"precision":0,"n_files":1,"n_statements":94,"n_excluded":4,"n_missing":1,"n_branches":30,"n_partial_branches":3,"n_missing_branches":3}}},"z_6167d61523e461a5_response_py":{"hash":"531af68f1e15ffd0f2bbafe39d50bbed","index":{"url":"z_6167d61523e461a5_response_py.html","file":"scrapy\\utils\\response.py","description":"","nums":{"precision":0,"n_files":1,"n_statements":51,"n_excluded":3,"n_missing":3,"n_branches":14,"n_partial_branches":2,"n_missing_branches":4}}},"z_6167d61523e461a5_serialize_py":{"hash":"029baf36153e7834f62a53a8db5ef345","index":{"url":"z_6167d61523e461a5_serialize_py.html","file":"scrapy\\utils\\serialize.py","description":"","nums":{"precision":0,"n_files":1,"n_statements":36,"n_excluded":0,"n_missing":2,"n_branches":18,"n_partial_branches":0,"n_missing_branches":0}}},"z_6167d61523e461a5_signal_py":{"hash":"93b28a0b0a8671fc850bd4e32a04e859","index":{"url":"z_6167d61523e461a5_signal_py.html","file":"scrapy\\utils\\signal.py","description":"","nums":{"precision":0,"n_files":1,"n_statements":50,"n_excluded":0,"n_missing":0,"n_branches":10,"n_partial_branches":1,"n_missing_branches":1}}},"z_6167d61523e461a5_sitemap_py":{"hash":"8aa4330e2c08731ff1223e1d280d9ca7","index":{"url":"z_6167d61523e461a5_sitemap_py.html","file":"scrapy\\utils\\sitemap.py","description":"","nums":{"precision":0,"n_files":1,"n_statements":29,"n_excluded":2,"n_missing":0,"n_branches":14,"n_partial_branches":1,"n_missing_branches":1}}},"z_6167d61523e461a5_spider_py":{"hash":"9064ff3be38737d165c7e1e84d83ef62","index":{"url":"z_6167d61523e461a5_spider_py.html","file":"scrapy\\utils\\spider.py","description":"","nums":{"precision":0,"n_files":1,"n_statements":44,"n_excluded":6,"n_missing":3,"n_branches":26,"n_partial_branches":9,"n_missing_branches":9}}},"z_6167d61523e461a5_ssl_py":{"hash":"b72546d85cf8bf072fc46a0e10758cbd","index":{"url":"z_6167d61523e461a5_ssl_py.html","file":"scrapy\\utils\\ssl.py","description":"","nums":{"precision":0,"n_files":1,"n_statements":44,"n_excluded":2,"n_missing":25,"n_branches":14,"n_partial_branches":1,"n_missing_branches":13}}},"z_6167d61523e461a5_template_py":{"hash":"812a2612568fae74f25ec41b8c87f08c","index":{"url":"z_6167d61523e461a5_template_py.html","file":"scrapy\\utils\\template.py","description":"","nums":{"precision":0,"n_files":1,"n_statements":16,"n_excluded":2,"n_missing":0,"n_branches":2,"n_partial_branches":0,"n_missing_branches":0}}},"z_6167d61523e461a5_test_py":{"hash":"4c1ec05ddc7bb1553542d749ebfa4260","index":{"url":"z_6167d61523e461a5_test_py.html","file":"scrapy\\utils\\test.py","description":"","nums":{"precision":0,"n_files":1,"n_statements":82,"n_excluded":6,"n_missing":20,"n_branches":6,"n_partial_branches":2,"n_missing_branches":4}}},"z_6167d61523e461a5_testproc_py":{"hash":"c2f10bafff8e53ad5f7434243e57b335","index":{"url":"z_6167d61523e461a5_testproc_py.html","file":"scrapy\\utils\\testproc.py","description":"","nums":{"precision":0,"n_files":1,"n_statements":43,"n_excluded":3,"n_missing":6,"n_branches":4,"n_partial_branches":2,"n_missing_branches":2}}},"z_6167d61523e461a5_testsite_py":{"hash":"4168b5fbceecdec1c3a57710dbff0a00","index":{"url":"z_6167d61523e461a5_testsite_py.html","file":"scrapy\\utils\\testsite.py","description":"","nums":{"precision":0,"n_files":1,"n_statements":31,"n_excluded":0,"n_missing":4,"n_branches":2,"n_partial_branches":1,"n_missing_branches":1}}},"z_6167d61523e461a5_trackref_py":{"hash":"73d0c716181f8cb6c74b638f752894ad","index":{"url":"z_6167d61523e461a5_trackref_py.html","file":"scrapy\\utils\\trackref.py","description":"","nums":{"precision":0,"n_files":1,"n_statements":39,"n_excluded":3,"n_missing":3,"n_branches":16,"n_partial_branches":4,"n_missing_branches":4}}},"z_6167d61523e461a5_url_py":{"hash":"e4a5794cd2468ff58fde2e182bc13f2f","index":{"url":"z_6167d61523e461a5_url_py.html","file":"scrapy\\utils\\url.py","description":"","nums":{"precision":0,"n_files":1,"n_statements":61,"n_excluded":3,"n_missing":1,"n_branches":14,"n_partial_branches":1,"n_missing_branches":1}}},"z_6167d61523e461a5_versions_py":{"hash":"a1e27ae130c24d54ad094cf375923796","index":{"url":"z_6167d61523e461a5_versions_py.html","file":"scrapy\\utils\\versions.py","description":"","nums":{"precision":0,"n_files":1,"n_statements":27,"n_excluded":0,"n_missing":2,"n_branches":8,"n_partial_branches":0,"n_missing_branches":0}}}}}